README.md
setup.py
neuro_scribe.egg-info/PKG-INFO
neuro_scribe.egg-info/SOURCES.txt
neuro_scribe.egg-info/dependency_links.txt
neuro_scribe.egg-info/requires.txt
neuro_scribe.egg-info/top_level.txt
neuroscribe/__init__.py
neuroscribe/version.py
neuroscribe/autodiff/__init__.py
neuroscribe/autodiff/executor.py
neuroscribe/autodiff/function.py
neuroscribe/autodiff/grad.py
neuroscribe/core/__init__.py
neuroscribe/core/_nn/__init__.py
neuroscribe/core/_nn/conv.py
neuroscribe/core/_nn/utils.py
neuroscribe/core/_tensor_lib/__init__.py
neuroscribe/core/_tensor_lib/_functional_api.py
neuroscribe/core/_tensor_lib/_tensor.py
neuroscribe/core/_tensor_lib/einsumfunc.py
neuroscribe/core/_tensor_lib/backend/__init__.py
neuroscribe/core/_tensor_lib/backend/cpu/__init__.py
neuroscribe/core/_tensor_lib/backend/cpu/cpu_backend.py
neuroscribe/core/_tensor_lib/backend/cpu/mlops.py
neuroscribe/core/_tensor_lib/backend/cuda/__init__.py
neuroscribe/core/_tensor_lib/backend/cuda/cuda_backend.py
neuroscribe/core/_tensor_lib/backend/cuda/mlops.py
neuroscribe/core/_tensor_lib/backend/mps/__init__.py
neuroscribe/core/_tensor_lib/backend/mps/mlops.py
neuroscribe/core/_tensor_lib/backend/mps/mps_backend.py
neuroscribe/core/_utils/__init__.py
neuroscribe/core/_utils/_data.py
neuroscribe/nn/__init__.py
neuroscribe/nn/functional.py
neuroscribe/nn/init.py
neuroscribe/nn/modules/__init__.py
neuroscribe/nn/modules/activation.py
neuroscribe/nn/modules/container.py
neuroscribe/nn/modules/conv.py
neuroscribe/nn/modules/linear.py
neuroscribe/nn/modules/loss.py
neuroscribe/nn/modules/module.py
neuroscribe/nn/simplified/__init__.py
neuroscribe/nn/simplified/conv.py
neuroscribe/nn/simplified/dense.py
neuroscribe/nn/simplified/sequential.py
neuroscribe/nn/simplified/utils.py
neuroscribe/optim/__init__.py
neuroscribe/optim/adam.py
neuroscribe/optim/optimizer.py
neuroscribe/optim/sgd.py
neuroscribe/utils/__init__.py
neuroscribe/utils/metrics.py
neuroscribe/utils/plot.py
neuroscribe/utils/data/__init__.py
neuroscribe/utils/data/data_loader.py
neuroscribe/utils/data/datasets.py
neuroscribe/utils/data/transforms.py
neuroscribe/utils/data/utils.py
test/test_engine.py