Metadata-Version: 2.1
Name: neuro-scribe
Version: 0.2.0
Summary: NeuroScribe - a lightweight deep learning framework.
Author: Ghaith Husrieh
Project-URL: Source, https://github.com/Ghaith-Husrieh/NeuroScribe
Classifier: Programming Language :: Python :: 3.12
Classifier: Operating System :: OS Independent
Requires-Python: >=3.12
Requires-Dist: numpy==1.26.4
Requires-Dist: tqdm==4.65.0
Requires-Dist: requests==2.31.0
Requires-Dist: plotly==5.22.0
Requires-Dist: cupy-cuda12x==13.0.0
Requires-Dist: fastrlock==0.8.2
